pykismet.py
pykismet3.py
pykismet3-0.1.1.dist-info/METADATA
pykismet3-0.1.1.dist-info/WHEEL
pykismet3-0.1.1.dist-info/metadata.json
pykismet3-0.1.1.dist-info/top_level.txt
pykismet3-0.1.1.dist-info/RECORD
pykismet3-0.1.1.dist-info/DESCRIPTION.rst
