Metadata-Version: 1.1
Name: pykismet3
Version: 0.1.1
Summary: A Python 3 module for the Akismet spam comment-spam-detection web service.
Home-page: https://github.com/grundleborg/pykismet3
Author: George Goldberg
Author-email: george@grundleborg.com
License: MIT
Platform: UNKNOWN
Classifier: Development Status :: 2 - Pre-Alpha
Classifier: Intended Audience :: Developers
Classifier: Natural Language :: English
Classifier: License :: OSI Approved :: MIT License
Classifier: Operating System :: OS Independent
Classifier: Programming Language :: Python
Classifier: Programming Language :: Python :: 3
Classifier: Programming Language :: Python :: 3.3
Classifier: Topic :: Software Development :: Libraries :: Python Modules
